nhc2_coco_2/__init__.py
nhc2_coco_2/coco.py
nhc2_coco_2/coco_ca.pem
nhc2_coco_2/coco_climate.py
nhc2_coco_2/coco_device_class.py
nhc2_coco_2/coco_discover.py
nhc2_coco_2/coco_discover_profiles.py
nhc2_coco_2/coco_entity.py
nhc2_coco_2/coco_fan.py
nhc2_coco_2/coco_fan_speed.py
nhc2_coco_2/coco_generic.py
nhc2_coco_2/coco_light.py
nhc2_coco_2/coco_login_validation.py
nhc2_coco_2/coco_profiles.py
nhc2_coco_2/coco_shutter.py
nhc2_coco_2/coco_switch.py
nhc2_coco_2/coco_switched_fan.py
nhc2_coco_2/const.py
nhc2_coco_2/helpers.py
nhc2_coco_2/tests/credentials_example.py
nhc2_coco_2/tests/discover_profiles.py
nhc2_coco_2/tests/discover_profiles_by_host.py
nhc2_coco_2/tests/test_example.py
nhc2_coco_2-1.4.7.dist-info/LICENSE
nhc2_coco_2-1.4.7.dist-info/METADATA
nhc2_coco_2-1.4.7.dist-info/WHEEL
nhc2_coco_2-1.4.7.dist-info/top_level.txt
nhc2_coco_2-1.4.7.dist-info/RECORD
