Metadata-Version: 2.1
Name: nhc2-coco-2
Version: 1.4.7
Summary: Python controller for a Niko Home Control II installation
Home-page: https://github.com/nielsvissers/nhc2-coco
Author: nielsvissers
Author-email: niels@wenn.be
License: UNKNOWN
Platform: UNKNOWN
License-File: LICENSE
Requires-Dist: get-mac (==0.8.2)
Requires-Dist: netifaces (==0.11.0)
Requires-Dist: paho-mqtt (==1.5.1)
